Workbook

Sheet Ecommerce_Data
A1: Order_ID | B1: Order_Date | C1: Customer_ID | D1: Customer_Name | E1: City | F1: State | G1: Product | H1: Category | I1: Sub_Category | J1: cost | K1: MRP | L1: Quantity | M1: Discount | N1: Revenue | O1: Total_cost | P1: Profit | Q1: Payment_Method | R1: Order_status | S1: Delivery_date | T1: Shipping_Delay | U1: Rating | V1: Returned | W1: Return_count
A2: ORD00452 | B2: 44927 | C2: CUST0188 | D2: Vikram | E2: Bangalore | F2: Karnataka | G2: Mixer | H2: Home | I2: Kitchen | J2: 4109 | K2: 4597.4149 | L2: 5 | M2: 0 | N2: =K2*L2*(1-M2/100) -> 22987.075 | O2: =J2*L2 -> 20545 | P2: =N2-O2 -> 2442.0746 | Q2: COD | R2: Delivered | S2: 44935 | T2: 5 | U2: 4 | V2: No | W2: =IF(AND(NOT(R2="Cancelled"),V2="Yes"),1,0) -> 0
A3: ORD00033 | B3: 44928 | C3: CUST0025 | D3: Priya | E3: Ahmedabad | F3: Gujarat | G3: Mixer | H3: Home | I3: Kitchen | J3: 5503 | K3: 8127.667 | L3: 2 | M3: 0 | N3: =K3*L3*(1-M3/100) -> 16255.334 | O3: =J3*L3 -> 11006 | P3: =N3-O3 -> 5249.3339 | Q3: Debit Card | R3: Delivered | S3: 44941 | T3: 6 | U3: 2 | V3: No | W3: =IF(AND(NOT(R3="Cancelled"),V3="Yes"),1,0) -> 0
A4: ORD00228 | B4: 44928 | C4: CUST0058 | D4: Kiran | E4: Ahmedabad | F4: Gujarat | G4: T-Shirt | H4: Clothing | I4: Men | J4: 563 | K4: 585.86996 | L4: 1 | M4: 15 | N4: =K4*L4*(1-M4/100) -> 497.98947 | O4: =J4*L4 -> 563 | P4: =N4-O4 -> -65.01053 | Q4: Credit Card | R4: Delivered | S4: 44934 | T4: 3 | U4: 3 | V4: No | W4: =IF(AND(NOT(R4="Cancelled"),V4="Yes"),1,0) -> 0
A5: ORD00372 | B5: 44928 | C5: CUST0178 | D5: Priya | E5: Chennai | F5: Tamil Nadu | G5: T-Shirt | H5: Clothing | I5: Men | J5: 505 | K5: 566.79693 | L5: 3 | M5: 5 | N5: =K5*L5*(1-M5/100) -> 1615.3712 | O5: =J5*L5 -> 1515 | P5: =N5-O5 -> 100.37125 | Q5: Debit Card | R5: Delivered | S5: 44935 | T5: 2 | U5: 5 | V5: No | W5: =IF(AND(NOT(R5="Cancelled"),V5="Yes"),1,0) -> 0
A6: ORD01079 | B6: 44928 | C6: CUST0127 | D6: Nikhil | E6: Pune | F6: Maharashtra | G6: T-Shirt | H6: Clothing | I6: Men | J6: 566 | K6: 743.87909 | L6: 3 | M6: 10 | N6: =K6*L6*(1-M6/100) -> 2008.4735 | O6: =J6*L6 -> 1698 | P6: =N6-O6 -> 310.47354 | Q6: COD | R6: Cancelled | T6: 8 | U6: 4 | W6: =IF(AND(NOT(R6="Cancelled"),V6="Yes"),1,0) -> 0
A7: ORD00980 | B7: 44929 | C7: CUST0263 | D7: Neha | E7: Hyderabad | F7: Telangana | G7: Mixer | H7: Home | I7: Kitchen | J7: 6377 | K7: 7324.9864 | L7: 1 | M7: 20 | N7: =K7*L7*(1-M7/100) -> 5859.9891 | O7: =J7*L7 -> 6377 | P7: =N7-O7 -> -517.01088 | Q7: Debit Card | R7: Delivered | S7: 44937 | T7: 5 | U7: 2 | V7: No | W7: =IF(AND(NOT(R7="Cancelled"),V7="Yes"),1,0) -> 0
A8: ORD01015 | B8: 44929 | C8: CUST0174 | D8: Sneha | E8: Ahmedabad | F8: Gujarat | G8: Mixer | H8: Home | I8: Kitchen | J8: 5122 | K8: 7138.7011 | L8: 3 | M8: 10 | N8: =K8*L8*(1-M8/100) -> 19274.493 | O8: =J8*L8 -> 15366 | P8: =N8-O8 -> 3908.4931 | Q8: COD | R8: Delivered | S8: 44937 | T8: 5 | U8: 4 | V8: No | W8: =IF(AND(NOT(R8="Cancelled"),V8="Yes"),1,0) -> 0
A9: ORD00191 | B9: 44930 | C9: CUST0015 | D9: Kiran | E9: Ahmedabad | F9: Gujarat | G9: T-Shirt | H9: Clothing | I9: Men | J9: 389 | K9: 486.42563 | L9: 3 | M9: 0 | N9: =K9*L9*(1-M9/100) -> 1459.2769 | O9: =J9*L9 -> 1167 | P9: =N9-O9 -> 292.27688 | Q9: COD | R9: Cancelled | T9: 7 | U9: 2 | W9: =IF(AND(NOT(R9="Cancelled"),V9="Yes"),1,0) -> 0
A10: ORD00344 | B10: 44930 | C10: CUST0126 | D10: Priya | E10: Mumbai | F10: Maharashtra | G10: Dress | H10: Clothing | I10: Women | J10: 804 | K10: 823.5958 | L10: 4 | M10: 15 | N10: =K10*L10*(1-M10/100) -> 2800.2257 | O10: =J10*L10 -> 3216 | P10: =N10-O10 -> -415.77428 | Q10: COD | R10: Delivered | S10: 44942 | T10: 5 | U10: 2 | V10: No | W10: =IF(AND(NOT(R10="Cancelled"),V10="Yes"),1,0) -> 0
A11: ORD00408 | B11: 44930 | C11: CUST0116 | D11: Manoj | E11: Hyderabad | F11: Telangana | G11: Headphones | H11: Electronics | I11: Accessories | J11: 1025 | K11: 1706.6954 | L11: 5 | M11: 5 | N11: =K11*L11*(1-M11/100) -> 8106.8031 | O11: =J11*L11 -> 5125 | P11: =N11-O11 -> 2981.8031 | Q11: Debit Card | R11: Delivered | S11: 44943 | T11: 6 | U11: 2 | V11: No | W11: =IF(AND(NOT(R11="Cancelled"),V11="Yes"),1,0) -> 0
A12: ORD00423 | B12: 44930 | C12: CUST0139 | D12: Priya | E12: Delhi | F12: Delhi | G12: Shoes | H12: Clothing | I12: Footwear | J12: 722 | K12: 1293.6534 | L12: 4 | M12: 20 | N12: =K12*L12*(1-M12/100) -> 4139.6908 | O12: =J12*L12 -> 2888 | P12: =N12-O12 -> 1251.6908 | Q12: UPI | R12: Cancelled | T12: 9 | U12: 1 | W12: =IF(AND(NOT(R12="Cancelled"),V12="Yes"),1,0) -> 0
A13: ORD01167 | B13: 44930 | C13: CUST0176 | D13: Rahul | E13: Ahmedabad | F13: Gujarat | G13: Sofa | H13: Home | I13: Furniture | J13: 35408 | K13: 49239.02 | L13: 2 | M13: 0 | N13: =K13*L13*(1-M13/100) -> 98478.041 | O13: =J13*L13 -> 70816 | P13: =N13-O13 -> 27662.041 | Q13: UPI | R13: Delivered | S13: 44939 | T13: 6 | U13: 4 | V13: Yes | W13: =IF(AND(NOT(R13="Cancelled"),V13="Yes"),1,0) -> 1
A14: ORD00353 | B14: 44931 | C14: CUST0065 | D14: Sneha | E14: Ahmedabad | F14: Gujarat | G14: Jeans | H14: Clothing | I14: Men | J14: 892 | K14: 1458.3971 | L14: 4 | M14: 0 | N14: =K14*L14*(1-M14/100) -> 5833.5884 | O14: =J14*L14 -> 3568 | P14: =N14-O14 -> 2265.5884 | Q14: UPI | R14: Cancelled | T14: 8 | U14: 2 | W14: =IF(AND(NOT(R14="Cancelled"),V14="Yes"),1,0) -> 0
A15: ORD00533 | B15: 44931 | C15: CUST0231 | D15: Nikhil | E15: Delhi | F15: Delhi | G15: Jeans | H15: Clothing | I15: Men | J15: 1265 | K15: 2090.3878 | L15: 3 | M15: 5 | N15: =K15*L15*(1-M15/100) -> 5957.6052 | O15: =J15*L15 -> 3795 | P15: =N15-O15 -> 2162.6052 | Q15: Credit Card | R15: Cancelled | T15: 8 | U15: 3 | W15: =IF(AND(NOT(R15="Cancelled"),V15="Yes"),1,0) -> 0
A16: ORD00022 | B16: 44932 | C16: CUST0256 | D16: Priya | E16: Ahmedabad | F16: Gujarat | G16: Face Cream | H16: Beauty | I16: Skincare | J16: 480 | K16: 531.52966 | L16: 3 | M16: 5 | N16: =K16*L16*(1-M16/100) -> 1514.8595 | O16: =J16*L16 -> 1440 | P16: =N16-O16 -> 74.859526 | Q16: Debit Card | R16: Delivered | S16: 44943 | T16: 6 | U16: 4 | V16: Yes | W16: =IF(AND(NOT(R16="Cancelled"),V16="Yes"),1,0) -> 1
A17: ORD00681 | B17: 44932 | C17: CUST0175 | D17: Arjun | E17: Delhi | F17: Delhi | G17: Shoes | H17: Clothing | I17: Footwear | J17: 1200 | K17: 1293.9325 | L17: 5 | M17: 0 | N17: =K17*L17*(1-M17/100) -> 6469.6627 | O17: =J17*L17 -> 6000 | P17: =N17-O17 -> 469.66268 | Q17: Credit Card | R17: Cancelled | T17: 7 | U17: 3 | W17: =IF(AND(NOT(R17="Cancelled"),V17="Yes"),1,0) -> 0
A18: ORD00020 | B18: 44933 | C18: CUST0232 | D18: Swathi | E18: Chennai | F18: Tamil Nadu | G18: Perfume | H18: Beauty | I18: Fragrance | J18: 649 | K18: 818.41543 | L18: 4 | M18: 20 | N18: =K18*L18*(1-M18/100) -> 2618.9294 | O18: =J18*L18 -> 2596 | P18: =N18-O18 -> 22.929362 | Q18: Debit Card | R18: Delivered | S18: 44942 | T18: 6 | U18: 4 | V18: Yes | W18: =IF(AND(NOT(R18="Cancelled"),V18="Yes"),1,0) -> 1
A19: ORD00094 | B19: 44933 | C19: CUST0101 | D19: Nikhil | E19: Delhi | F19: Delhi | G19: Perfume | H19: Beauty | I19: Fragrance | J19: 545 | K19: 647.07394 | L19: 3 | M19: 10 | N19: =K19*L19*(1-M19/100) -> 1747.0996 | O19: =J19*L19 -> 1635 | P19: =N19-O19 -> 112.09964 | Q19: UPI | R19: Delivered | S19: 44937 | T19: 1 | U19: 5 | V19: No | W19: =IF(AND(NOT(R19="Cancelled"),V19="Yes"),1,0) -> 0
A20: ORD00127 | B20: 44933 | C20: CUST0252 | D20: Swathi | E20: Kolkata | F20: West Bengal | G20: T-Shirt | H20: Clothing | I20: Men | J20: 658 | K20: 1051.9265 | L20: 5 | M20: 15 | N20: =K20*L20*(1-M20/100) -> 4470.6876 | O20: =J20*L20 -> 3290 | P20: =N20-O20 -> 1180.6876 | Q20: UPI | R20: Delivered | S20: 44944 | T20: 6 | U20: 3 | V20: No | W20: =IF(AND(NOT(R20="Cancelled"),V20="Yes"),1,0) -> 0
A21: ORD00915 | B21: 44933 | C21: CUST0204 | D21: Rohit | E21: Mumbai | F21: Maharashtra | G21: T-Shirt | H21: Clothing | I21: Men | J21: 525 | K21: 644.78263 | L21: 1 | M21: 20 | N21: =K21*L21*(1-M21/100) -> 515.82611 | O21: =J21*L21 -> 525 | P21: =N21-O21 -> -9.1738933 | Q21: Credit Card | R21: Cancelled | T21: 9 | U21: 1 | W21: =IF(AND(NOT(R21="Cancelled"),V21="Yes"),1,0) -> 0
A22: ORD00947 | B22: 44933 | C22: CUST0027 | D22: Rahul | E22: Bangalore | F22: Karnataka | G22: Samsung TV | H22: Electronics | I22: TV | J22: 41871 | K22: 52186.75 | L22: 5 | M22: 5 | N22: =K22*L22*(1-M22/100) -> 247887.06 | O22: =J22*L22 -> 209355 | P22: =N22-O22 -> 38532.06 | Q22: Debit Card | R22: Delivered | S22: 44938 | T22: 1 | U22: 5 | V22: No | W22: =IF(AND(NOT(R22="Cancelled"),V22="Yes"),1,0) -> 0
A23: ORD00104 | B23: 44934 | C23: CUST0256 | D23: Rahul | E23: Chennai | F23: Tamil Nadu | G23: Shoes | H23: Clothing | I23: Footwear | J23: 1585 | K23: 1916.8904 | L23: 1 | M23: 5 | N23: =K23*L23*(1-M23/100) -> 1821.0459 | O23: =J23*L23 -> 1585 | P23: =N23-O23 -> 236.04592 | Q23: Debit Card | R23: Delivered | S23: 44945 | T23: 6 | U23: 2 | V23: No | W23: =IF(AND(NOT(R23="Cancelled"),V23="Yes"),1,0) -> 0
A24: ORD00235 | B24: 44934 | C24: CUST0253 | D24: Swathi | E24: Ahmedabad | F24: Gujarat | G24: iPhone 14 | H24: Electronics | I24: Mobile | J24: 74443 | K24: 99616.634 | L24: 2 | M24: 5 | N24: =K24*L24*(1-M24/100) -> 189271.6 | O24: =J24*L24 -> 148886 | P24: =N24-O24 -> 40385.604 | Q24: Credit Card | R24: Delivered | S24: 44947 | T24: 6 | U24: 4 | V24: Yes | W24: =IF(AND(NOT(R24="Cancelled"),V24="Yes"),1,0) -> 1
A25: ORD00623 | B25: 44934 | C25: CUST0164 | D25: Rohit | E25: Hyderabad | F25: Telangana | G25: Mixer | H25: Home | I25: Kitchen | J25: 4882 | K25: 6220.9146 | L25: 1 | M25: 0 | N25: =K25*L25*(1-M25/100) -> 6220.9146 | O25: =J25*L25 -> 4882 | P25: =N25-O25 -> 1338.9146 | Q25: UPI | R25: Delivered | S25: 44941 | T25: 1 | U25: 4 | V25: No | W25: =IF(AND(NOT(R25="Cancelled"),V25="Yes"),1,0) -> 0
A26: ORD00053 | B26: 44935 | C26: CUST0176 | D26: Manoj | E26: Kolkata | F26: West Bengal | G26: Mixer | H26: Home | I26: Kitchen | J26: 3475 | K26: 5066.5993 | L26: 4 | M26: 20 | N26: =K26*L26*(1-M26/100) -> 16213.118 | O26: =J26*L26 -> 13900 | P26: =N26-O26 -> 2313.1178 | Q26: Credit Card | R26: Cancelled | T26: 9 | U26: 1 | W26: =IF(AND(NOT(R26="Cancelled"),V26="Yes"),1,0) -> 0
A27: ORD00422 | B27: 44935 | C27: CUST0117 | D27: Vikram | E27: Bangalore | F27: Karnataka | G27: Face Cream | H27: Beauty | I27: Skincare | J27: 221 | K27: 375.7334 | L27: 5 | M27: 20 | N27: =K27*L27*(1-M27/100) -> 1502.9336 | O27: =J27*L27 -> 1105 | P27: =N27-O27 -> 397.93362 | Q27: Credit Card | R27: Delivered | S27: 44948 | T27: 6 | U27: 4 | V27: Yes | W27: =IF(AND(NOT(R27="Cancelled"),V27="Yes"),1,0) -> 1
A28: ORD00666 | B28: 44935 | C28: CUST0002 | D28: Neha | E28: Ahmedabad | F28: Gujarat | G28: Shoes | H28: Clothing | I28: Footwear | J28: 777 | K28: 1141.1981 | L28: 5 | M28: 0 | N28: =K28*L28*(1-M28/100) -> 5705.9907 | O28: =J28*L28 -> 3885 | P28: =N28-O28 -> 1820.9907 | Q28: UPI | R28: Delivered | S28: 44943 | T28: 1 | U28: 4 | V28: No | W28: =IF(AND(NOT(R28="Cancelled"),V28="Yes"),1,0) -> 0
A29: ORD01023 | B29: 44935 | C29: CUST0242 | D29: Pooja | E29: Mumbai | F29: Maharashtra | G29: Headphones | H29: Electronics | I29: Accessories | J29: 1018 | K29: 1111.6081 | L29: 1 | M29: 0 | N29: =K29*L29*(1-M29/100) -> 1111.6081 | O29: =J29*L29 -> 1018 | P29: =N29-O29 -> 93.608139 | Q29: Credit Card | R29: Cancelled | T29: 10 | U29: 1 | W29: =IF(AND(NOT(R29="Cancelled"),V29="Yes"),1,0) -> 0
A30: ORD00257 | B30: 44937 | C30: CUST0300 | D30: Divya | E30: Chennai | F30: Tamil Nadu | G30: Laptop | H30: Electronics | I30: Computers | J30: 40754 | K30: 68727.394 | L30: 5 | M30: 20 | N30: =K30*L30*(1-M30/100) -> 274909.58 | O30: =J30*L30 -> 203770 | P30: =N30-O30 -> 71139.575 | Q30: COD | R30: Delivered | S30: 44947 | T30: 4 | U30: 2 | V30: No | W30: =IF(AND(NOT(R30="Cancelled"),V30="Yes"),1,0) -> 0
A31: ORD00645 | B31: 44937 | C31: CUST0232 | D31: Divya | E31: Mumbai | F31: Maharashtra | G31: Perfume | H31: Beauty | I31: Fragrance | J31: 630 | K31: 717.22826 | L31: 2 | M31: 5 | N31: =K31*L31*(1-M31/100) -> 1362.7337 | O31: =J31*L31 -> 1260 | P31: =N31-O31 -> 102.73369 | Q31: UPI | R31: Delivered | S31: 44941 | T31: 1 | U31: 4 | V31: No | W31: =IF(AND(NOT(R31="Cancelled"),V31="Yes"),1,0) -> 0
A32: ORD00990 | B32: 44937 | C32: CUST0012 | D32: Arjun | E32: Delhi | F32: Delhi | G32: Jeans | H32: Clothing | I32: Men | J32: 1359 | K32: 1586.636 | L32: 4 | M32: 20 | N32: =K32*L32*(1-M32/100) -> 5077.2353 | O32: =J32*L32 -> 5436 | P32: =N32-O32 -> -358.76466 | Q32: UPI | R32: Delivered | S32: 44944 | T32: 1 | U32: 5 | V32: No | W32: =IF(AND(NOT(R32="Cancelled"),V32="Yes"),1,0) -> 0
A33: ORD01097 | B33: 44937 | C33: CUST0249 | D33: Amit | E33: Delhi | F33: Delhi | G33: Shoes | H33: Clothing | I33: Footwear | J33: 1367 | K33: 1607.0226 | L33: 5 | M33: 5 | N33: =K33*L33*(1-M33/100) -> 7633.3575 | O33: =J33*L33 -> 6835 | P33: =N33-O33 -> 798.35748 | Q33: Debit Card | R33: Cancelled | T33: 9 | U33: 1 | W33: =IF(AND(NOT(R33="Cancelled"),V33="Yes"),1,0) -> 0
A34: ORD00163 | B34: 44938 | C34: CUST0178 | D34: Kavya | E34: Ahmedabad | F34: Gujarat | G34: Jeans | H34: Clothing | I34: Men | J34: 1430 | K34: 1439.4545 | L34: 1 | M34: 15 | N34: =K34*L34*(1-M34/100) -> 1223.5363 | O34: =J34*L34 -> 1430 | P34: =N34-O34 -> -206.4637 | Q34: UPI | R34: Delivered | S34: 44946 | T34: 3 | U34: 2 | V34: No | W34: =IF(AND(NOT(R34="Cancelled"),V34="Yes"),1,0) -> 0
A35: ORD01113 | B35: 44938 | C35: CUST0176 | D35: Ramesh | E35: Chennai | F35: Tamil Nadu | G35: Perfume | H35: Beauty | I35: Fragrance | J35: 619 | K35: 1067.2682 | L35: 2 | M35: 15 | N35: =K35*L35*(1-M35/100) -> 1814.3559 | O35: =J35*L35 -> 1238 | P35: =N35-O35 -> 576.3559 | Q35: UPI | R35: Delivered | S35: 44947 | T35: 4 | U35: 4 | V35: No | W35: =IF(AND(NOT(R35="Cancelled"),V35="Yes"),1,0) -> 0
A36: ORD00011 | B36: 44939 | C36: CUST0294 | D36: Kavya | E36: Ahmedabad | F36: Gujarat | G36: Face Cream | H36: Beauty | I36: Skincare | J36: 578 | K36: 609.40131 | L36: 4 | M36: 10 | N36: =K36*L36*(1-M36/100) -> 2193.8447 | O36: =J36*L36 -> 2312 | P36: =N36-O36 -> -118.15529 | Q36: COD | R36: Delivered | S36: 44948 | T36: 2 | U36: 4 | V36: No | W36: =IF(AND(NOT(R36="Cancelled"),V36="Yes"),1,0) -> 0
A37: ORD00108 | B37: 44939 | C37: CUST0018 | D37: Kavya | E37: Delhi | F37: Delhi | G37: iPhone 14 | H37: Electronics | I37: Mobile | J37: 71289 | K37: 109285.29 | L37: 2 | M37: 15 | N37: =K37*L37*(1-M37/100) -> 185784.99 | O37: =J37*L37 -> 142578 | P37: =N37-O37 -> 43206.986 | Q37: COD | R37: Delivered | S37: 44952 | T37: 6 | U37: 4 | V37: Yes | W37: =IF(AND(NOT(R37="Cancelled"),V37="Yes"),1,0) -> 1
A38: ORD00234 | B38: 44939 | C38: CUST0292 | D38: Divya | E38: Mumbai | F38: Maharashtra | G38: Headphones | H38: Electronics | I38: Accessories | J38: 1220 | K38: 1373.6526 | L38: 3 | M38: 0 | N38: =K38*L38*(1-M38/100) -> 4120.9578 | O38: =J38*L38 -> 3660 | P38: =N38-O38 -> 460.95778 | Q38: COD | R38: Cancelled | T38: 8 | U38: 2 | W38: =IF(AND(NOT(R38="Cancelled"),V38="Yes"),1,0) -> 0
A39: ORD00281 | B39: 44939 | C39: CUST0175 | D39: Manoj | E39: Pune | F39: Maharashtra | G39: Face Cream | H39: Beauty | I39: Skincare | J39: 410 | K39: 434.20316 | L39: 3 | M39: 15 | N39: =K39*L39*(1-M39/100) -> 1107.2181 | O39: =J39*L39 -> 1230 | P39: =N39-O39 -> -122.78194 | Q39: UPI | R39: Cancelled | T39: 9 | U39: 1 | W39: =IF(AND(NOT(R39="Cancelled"),V39="Yes"),1,0) -> 0
A40: ORD00333 | B40: 44939 | C40: CUST0057 | D40: Divya | E40: Pune | F40: Maharashtra | G40: Perfume | H40: Beauty | I40: Fragrance | J40: 584 | K40: 738.19974 | L40: 5 | M40: 10 | N40: =K40*L40*(1-M40/100) -> 3321.8988 | O40: =J40*L40 -> 2920 | P40: =N40-O40 -> 401.89884 | Q40: Debit Card | R40: Delivered | S40: 44948 | T40: 6 | U40: 4 | V40: Yes | W40: =IF(AND(NOT(R40="Cancelled"),V40="Yes"),1,0) -> 1
A41: ORD00629 | B41: 44939 | C41: CUST0208 | D41: Rohit | E41: Hyderabad | F41: Telangana | G41: Dress | H41: Clothing | I41: Women | J41: 1534 | K41: 2104.4993 | L41: 4 | M41: 5 | N41: =K41*L41*(1-M41/100) -> 7997.0974 | O41: =J41*L41 -> 6136 | P41: =N41-O41 -> 1861.0974 | Q41: Debit Card | R41: Delivered | S41: 44948 | T41: 3 | U41: 4 | V41: No | W41: =IF(AND(NOT(R41="Cancelled"),V41="Yes"),1,0) -> 0
A42: ORD00664 | B42: 44939 | C42: CUST0212 | D42: Nikhil | E42: Mumbai | F42: Maharashtra | G42: Shoes | H42: Clothing | I42: Footwear | J42: 2769 | K42: 4256.3822 | L42: 4 | M42: 0 | N42: =K42*L42*(1-M42/100) -> 17025.529 | O42: =J42*L42 -> 11076 | P42: =N42-O42 -> 5949.5289 | Q42: Credit Card | R42: Delivered | S42: 44947 | T42: 1 | U42: 4 | V42: No | W42: =IF(AND(NOT(R42="Cancelled"),V42="Yes"),1,0) -> 0
A43: ORD00791 | B43: 44939 | C43: CUST0249 | D43: Swathi | E43: Pune | F43: Maharashtra | G43: iPhone 14 | H43: Electronics | I43: Mobile | J43: 69697 | K43: 97625.536 | L43: 2 | M43: 10 | N43: =K43*L43*(1-M43/100) -> 175725.96 | O43: =J43*L43 -> 139394 | P43: =N43-O43 -> 36331.964 | Q43: Credit Card | R43: Delivered | S43: 44946 | T43: 4 | U43: 4 | V43: No | W43: =IF(AND(NOT(R43="Cancelled"),V43="Yes"),1,0) -> 0
A44: ORD00313 | B44: 44940 | C44: CUST0114 | D44: Kiran | E44: Delhi | F44: Delhi | G44: T-Shirt | H44: Clothing | I44: Men | J44: 748 | K44: 829.43945 | L44: 2 | M44: 5 | N44: =K44*L44*(1-M44/100) -> 1575.935 | O44: =J44*L44 -> 1496 | P44: =N44-O44 -> 79.934955 | Q44: Debit Card | R44: Delivered | S44: 44945 | T44: 1 | U44: 4 | V44: No | W44: =IF(AND(NOT(R44="Cancelled"),V44="Yes"),1,0) -> 0
A45: ORD00462 | B45: 44940 | C45: CUST0048 | D45: Rohit | E45: Hyderabad | F45: Telangana | G45: Perfume | H45: Beauty | I45: Fragrance | J45: 611 | K45: 666.75911 | L45: 5 | M45: 0 | N45: =K45*L45*(1-M45/100) -> 3333.7956 | O45: =J45*L45 -> 3055 | P45: =N45-O45 -> 278.79556 | Q45: UPI | R45: Delivered | S45: 44947 | T45: 4 | U45: 4 | V45: No | W45: =IF(AND(NOT(R45="Cancelled"),V45="Yes"),1,0) -> 0
A46: ORD00307 | B46: 44941 | C46: CUST0066 | D46: Rahul | E46: Mumbai | F46: Maharashtra | G46: Dress | H46: Clothing | I46: Women | J46: 1131 | K46: 1489.0926 | L46: 1 | M46: 10 | N46: =K46*L46*(1-M46/100) -> 1340.1834 | O46: =J46*L46 -> 1131 | P46: =N46-O46 -> 209.18337 | Q46: Credit Card | R46: Cancelled | T46: 8 | U46: 4 | W46: =IF(AND(NOT(R46="Cancelled"),V46="Yes"),1,0) -> 0
A47: ORD00536 | B47: 44941 | C47: CUST0049 | D47: Sneha | E47: Hyderabad | F47: Telangana | G47: Jeans | H47: Clothing | I47: Men | J47: 1349 | K47: 1425.865 | L47: 4 | M47: 0 | N47: =K47*L47*(1-M47/100) -> 5703.46 | O47: =J47*L47 -> 5396 | P47: =N47-O47 -> 307.45997 | Q47: COD | R47: Cancelled | T47: 8 | U47: 2 | W47: =IF(AND(NOT(R47="Cancelled"),V47="Yes"),1,0) -> 0
A48: ORD00667 | B48: 44941 | C48: CUST0150 | D48: Sneha | E48: Mumbai | F48: Maharashtra | G48: Dress | H48: Clothing | I48: Women | J48: 1908 | K48: 3032.0515 | L48: 3 | M48: 20 | N48: =K48*L48*(1-M48/100) -> 7276.9236 | O48: =J48*L48 -> 5724 | P48: =N48-O48 -> 1552.9236 | Q48: COD | R48: Cancelled | T48: 9 | U48: 1 | W48: =IF(AND(NOT(R48="Cancelled"),V48="Yes"),1,0) -> 0
A49: ORD00836 | B49: 44941 | C49: CUST0244 | D49: Swathi | E49: Mumbai | F49: Maharashtra | G49: Headphones | H49: Electronics | I49: Accessories | J49: 1577 | K49: 2134.9896 | L49: 1 | M49: 20 | N49: =K49*L49*(1-M49/100) -> 1707.9917 | O49: =J49*L49 -> 1577 | P49: =N49-O49 -> 130.99167 | Q49: Debit Card | R49: Delivered | S49: 44948 | T49: 1 | U49: 5 | V49: No | W49: =IF(AND(NOT(R49="Cancelled"),V49="Yes"),1,0) -> 0
A50: ORD00971 | B50: 44941 | C50: CUST0084 | D50: Vikram | E50: Ahmedabad | F50: Gujarat | G50: Mixer | H50: Home | I50: Kitchen | J50: 6701 | K50: 7042.2805 | L50: 2 | M50: 10 | N50: =K50*L50*(1-M50/100) -> 12676.105 | O50: =J50*L50 -> 13402 | P50: =N50-O50 -> -725.89513 | Q50: COD | R50: Cancelled | T50: 10 | U50: 1 | W50: =IF(AND(NOT(R50="Cancelled"),V50="Yes"),1,0) -> 0
A51: ORD00509 | B51: 44942 | C51: CUST0121 | D51: Deepika | E51: Chennai | F51: Tamil Nadu | G51: T-Shirt | H51: Clothing | I51: Men | J51: 381 | K51: 671.3227 | L51: 1 | M51: 15 | N51: =K51*L51*(1-M51/100) -> 570.62429 | O51: =J51*L51 -> 381 | P51: =N51-O51 -> 189.62429 | Q51: Debit Card | R51: Cancelled | T51: 10 | U51: 1 | W51: =IF(AND(NOT(R51="Cancelled"),V51="Yes"),1,0) -> 0
A52: ORD00877 | B52: 44942 | C52: CUST0182 | D52: Meena | E52: Hyderabad | F52: Telangana | G52: Face Cream | H52: Beauty | I52: Skincare | J52: 509 | K52: 797.77916 | L52: 5 | M52: 15 | N52: =K52*L52*(1-M52/100) -> 3390.5614 | O52: =J52*L52 -> 2545 | P52: =N52-O52 -> 845.56142 | Q52: COD | R52: Cancelled | T52: 7 | U52: 2 | W52: =IF(AND(NOT(R52="Cancelled"),V52="Yes"),1,0) -> 0
A53: ORD00202 | B53: 44943 | C53: CUST0250 | D53: Rohit | E53: Delhi | F53: Delhi | G53: Samsung TV | H53: Electronics | I53: TV | J53: 68759 | K53: 75969.19 | L53: 3 | M53: 20 | N53: =K53*L53*(1-M53/100) -> 182326.05 | O53: =J53*L53 -> 206277 | P53: =N53-O53 -> -23950.945 | Q53: COD | R53: Delivered | S53: 44948 | T53: 1 | U53: 4 | V53: No | W53: =IF(AND(NOT(R53="Cancelled"),V53="Yes"),1,0) -> 0
A54: ORD00433 | B54: 44943 | C54: CUST0121 | D54: Anjali | E54: Hyderabad | F54: Telangana | G54: Dress | H54: Clothing | I54: Women | J54: 1397 | K54: 2018.8948 | L54: 4 | M54: 20 | N54: =K54*L54*(1-M54/100) -> 6460.4633 | O54: =J54*L54 -> 5588 | P54: =N54-O54 -> 872.46326 | Q54: Credit Card | R54: Delivered | S54: 44949 | T54: 3 | U54: 4 | V54: No | W54: =IF(AND(NOT(R54="Cancelled"),V54="Yes"),1,0) -> 0
A55: ORD00568 | B55: 44943 | C55: CUST0156 | D55: Swathi | E55: Ahmedabad | F55: Gujarat | G55: Jeans | H55: Clothing | I55: Men | J55: 1183 | K55: 1630.4628 | L55: 1 | M55: 5 | N55: =K55*L55*(1-M55/100) -> 1548.9397 | O55: =J55*L55 -> 1183 | P55: =N55-O55 -> 365.93967 | Q55: Credit Card | R55: Delivered | S55: 44953 | T55: 7 | U55: 4 | V55: Yes | W55: =IF(AND(NOT(R55="Cancelled"),V55="Yes"),1,0) -> 1
A56: ORD00774 | B56: 44943 | C56: CUST0208 | D56: Divya | E56: Chennai | F56: Tamil Nadu | G56: Jeans | H56: Clothing | I56: Men | J56: 1015 | K56: 1627.4574 | L56: 3 | M56: 0 | N56: =K56*L56*(1-M56/100) -> 4882.3721 | O56: =J56*L56 -> 3045 | P56: =N56-O56 -> 1837.3721 | Q56: Credit Card | R56: Delivered | S56: 44953 | T56: 5 | U56: 3 | V56: No | W56: =IF(AND(NOT(R56="Cancelled"),V56="Yes"),1,0) -> 0
A57: ORD00810 | B57: 44943 | C57: CUST0070 | D57: Ramesh | E57: Bangalore | F57: Karnataka | G57: Samsung TV | H57: Electronics | I57: TV | J57: 44360 | K57: 58318.186 | L57: 5 | M57: 15 | N57: =K57*L57*(1-M57/100) -> 247852.29 | O57: =J57*L57 -> 221800 | P57: =N57-O57 -> 26052.292 | Q57: Credit Card | R57: Cancelled | T57: 9 | U57: 1 | W57: =IF(AND(NOT(R57="Cancelled"),V57="Yes"),1,0) -> 0
A58: ORD00207 | B58: 44944 | C58: CUST0097 | D58: Amit | E58: Pune | F58: Maharashtra | G58: Jeans | H58: Clothing | I58: Men | J58: 994 | K58: 1054.0321 | L58: 2 | M58: 20 | N58: =K58*L58*(1-M58/100) -> 1686.4514 | O58: =J58*L58 -> 1988 | P58: =N58-O58 -> -301.54862 | Q58: COD | R58: Delivered | S58: 44952 | T58: 5 | U58: 3 | V58: No | W58: =IF(AND(NOT(R58="Cancelled"),V58="Yes"),1,0) -> 0
A59: ORD00258 | B59: 44944 | C59: CUST0191 | D59: Vikram | E59: Kolkata | F59: West Bengal | G59: Shoes | H59: Clothing | I59: Footwear | J59: 2678 | K59: 3729.9193 | L59: 2 | M59: 10 | N59: =K59*L59*(1-M59/100) -> 6713.8548 | O59: =J59*L59 -> 5356 | P59: =N59-O59 -> 1357.8548 | Q59: UPI | R59: Delivered | S59: 44953 | T59: 5 | U59: 4 | V59: No | W59: =IF(AND(NOT(R59="Cancelled"),V59="Yes"),1,0) -> 0
A60: ORD01121 | B60: 44944 | C60: CUST0264 | D60: Manoj | E60: Delhi | F60: Delhi | G60: Perfume | H60: Beauty | I60: Fragrance | J60: 734 | K60: 1067.7387 | L60: 2 | M60: 20 | N60: =K60*L60*(1-M60/100) -> 1708.382 | O60: =J60*L60 -> 1468 | P60: =N60-O60 -> 240.382 | Q60: COD | R60: Delivered | S60: 44955 | T60: 6 | U60: 3 | V60: No | W60: =IF(AND(NOT(R60="Cancelled"),V60="Yes"),1,0) -> 0
A61: ORD00310 | B61: 44945 | C61: CUST0278 | D61: Neha | E61: Chennai | F61: Tamil Nadu | G61: Shoes | H61: Clothing | I61: Footwear | J61: 2198 | K61: 3431.8375 | L61: 5 | M61: 10 | N61: =K61*L61*(1-M61/100) -> 15443.269 | O61: =J61*L61 -> 10990 | P61: =N61-O61 -> 4453.2689 | Q61: Credit Card | R61: Delivered | S61: 44949 | T61: 1 | U61: 4 | V61: No | W61: =IF(AND(NOT(R61="Cancelled"),V61="Yes"),1,0) -> 0
A62: ORD01099 | B62: 44945 | C62: CUST0215 | D62: Sneha | E62: Bangalore | F62: Karnataka | G62: Shoes | H62: Clothing | I62: Footwear | J62: 1657 | K62: 1901.834 | L62: 1 | M62: 15 | N62: =K62*L62*(1-M62/100) -> 1616.5589 | O62: =J62*L62 -> 1657 | P62: =N62-O62 -> -40.441131 | Q62: UPI | R62: Cancelled | T62: 9 | U62: 1 | W62: =IF(AND(NOT(R62="Cancelled"),V62="Yes"),1,0) -> 0
A63: ORD01147 | B63: 44945 | C63: CUST0034 | D63: Arjun | E63: Kolkata | F63: West Bengal | G63: Laptop | H63: Electronics | I63: Computers | J63: 34258 | K63: 35215.842 | L63: 1 | M63: 15 | N63: =K63*L63*(1-M63/100) -> 29933.465 | O63: =J63*L63 -> 34258 | P63: =N63-O63 -> -4324.5346 | Q63: COD | R63: Delivered | S63: 44954 | T63: 4 | U63: 3 | V63: No | W63: =IF(AND(NOT(R63="Cancelled"),V63="Yes"),1,0) -> 0
A64: ORD00446 | B64: 44946 | C64: CUST0289 | D64: Suresh | E64: Bangalore | F64: Karnataka | G64: Mixer | H64: Home | I64: Kitchen | J64: 6136 | K64: 7840.4568 | L64: 3 | M64: 20 | N64: =K64*L64*(1-M64/100) -> 18817.096 | O64: =J64*L64 -> 18408 | P64: =N64-O64 -> 409.09623 | Q64: UPI | R64: Delivered | S64: 44956 | T64: 6 | U64: 3 | V64: No | W64: =IF(AND(NOT(R64="Cancelled"),V64="Yes"),1,0) -> 0
A65: ORD00479 | B65: 44946 | C65: CUST0225 | D65: Divya | E65: Bangalore | F65: Karnataka | G65: Face Cream | H65: Beauty | I65: Skincare | J65: 309 | K65: 350.20775 | L65: 2 | M65: 5 | N65: =K65*L65*(1-M65/100) -> 665.39472 | O65: =J65*L65 -> 618 | P65: =N65-O65 -> 47.394716 | Q65: Debit Card | R65: Delivered | S65: 44955 | T65: 5 | U65: 4 | V65: No | W65: =IF(AND(NOT(R65="Cancelled"),V65="Yes"),1,0) -> 0
A66: ORD00624 | B66: 44946 | C66: CUST0239 | D66: Pooja | E66: Ahmedabad | F66: Gujarat | G66: Face Cream | H66: Beauty | I66: Skincare | J66: 417 | K66: 454.85068 | L66: 2 | M66: 5 | N66: =K66*L66*(1-M66/100) -> 864.21629 | O66: =J66*L66 -> 834 | P66: =N66-O66 -> 30.216292 | Q66: Credit Card | R66: Cancelled | T66: 8 | U66: 2 | W66: =IF(AND(NOT(R66="Cancelled"),V66="Yes"),1,0) -> 0
A67: ORD00883 | B67: 44946 | C67: CUST0291 | D67: Deepika | E67: Pune | F67: Maharashtra | G67: Sofa | H67: Home | I67: Furniture | J67: 40581 | K67: 63368.197 | L67: 3 | M67: 15 | N67: =K67*L67*(1-M67/100) -> 161588.9 | O67: =J67*L67 -> 121743 | P67: =N67-O67 -> 39845.902 | Q67: Credit Card | R67: Cancelled | T67: 9 | U67: 1 | W67: =IF(AND(NOT(R67="Cancelled"),V67="Yes"),1,0) -> 0
A68: ORD00290 | B68: 44947 | C68: CUST0167 | D68: Meena | E68: Kolkata | F68: West Bengal | G68: Dress | H68: Clothing | I68: Women | J68: 1856 | K68: 2644.9998 | L68: 2 | M68: 20 | N68: =K68*L68*(1-M68/100) -> 4231.9997 | O68: =J68*L68 -> 3712 | P68: =N68-O68 -> 519.99968 | Q68: Debit Card | R68: Delivered | S68: 44957 | T68: 6 | U68: 2 | V68: No | W68: =IF(AND(NOT(R68="Cancelled"),V68="Yes"),1,0) -> 0
A69: ORD00421 | B69: 44947 | C69: CUST0257 | D69: Neha | E69: Mumbai | F69: Maharashtra | G69: Jeans | H69: Clothing | I69: Men | J69: 1102 | K69: 1233.5814 | L69: 2 | M69: 0 | N69: =K69*L69*(1-M69/100) -> 2467.1628 | O69: =J69*L69 -> 2204 | P69: =N69-O69 -> 263.16277 | Q69: Debit Card | R69: Delivered | S69: 44955 | T69: 5 | U69: 2 | V69: No | W69: =IF(AND(NOT(R69="Cancelled"),V69="Yes"),1,0) -> 0
A70: ORD01126 | B70: 44948 | C70: CUST0001 | D70: Meena | E70: Kolkata | F70: West Bengal | G70: Perfume | H70: Beauty | I70: Fragrance | J70: 947 | K70: 1455.7021 | L70: 5 | M70: 10 | N70: =K70*L70*(1-M70/100) -> 6550.6594 | O70: =J70*L70 -> 4735 | P70: =N70-O70 -> 1815.6594 | Q70: COD | R70: Delivered | S70: 44957 | T70: 5 | U70: 4 | V70: No | W70: =IF(AND(NOT(R70="Cancelled"),V70="Yes"),1,0) -> 0
A71: ORD00241 | B71: 44949 | C71: CUST0285 | D71: Rohit | E71: Pune | F71: Maharashtra | G71: Shoes | H71: Clothing | I71: Footwear | J71: 1443 | K71: 2385.5568 | L71: 4 | M71: 0 | N71: =K71*L71*(1-M71/100) -> 9542.2271 | O71: =J71*L71 -> 5772 | P71: =N71-O71 -> 3770.2271 | Q71: UPI | R71: Delivered | S71: 44960 | T71: 6 | U71: 2 | V71: No | W71: =IF(AND(NOT(R71="Cancelled"),V71="Yes"),1,0) -> 0
A72: ORD00267 | B72: 44949 | C72: CUST0114 | D72: Nikhil | E72: Mumbai | F72: Maharashtra | G72: Laptop | H72: Electronics | I72: Computers | J72: 41686 | K72: 58852.798 | L72: 5 | M72: 5 | N72: =K72*L72*(1-M72/100) -> 279550.79 | O72: =J72*L72 -> 208430 | P72: =N72-O72 -> 71120.792 | Q72: Credit Card | R72: Delivered | S72: 44960 | T72: 4 | U72: 4 | V72: No | W72: =IF(AND(NOT(R72="Cancelled"),V72="Yes"),1,0) -> 0
A73: ORD00543 | B73: 44949 | C73: CUST0031 | D73: Priya | E73: Kolkata | F73: West Bengal | G73: Headphones | H73: Electronics | I73: Accessories | J73: 1186 | K73: 2095.6786 | L73: 5 | M73: 15 | N73: =K73*L73*(1-M73/100) -> 8906.6342 | O73: =J73*L73 -> 5930 | P73: =N73-O73 -> 2976.6342 | Q73: UPI | R73: Cancelled | T73: 10 | U73: 1 | W73: =IF(AND(NOT(R73="Cancelled"),V73="Yes"),1,0) -> 0
A74: ORD00600 | B74: 44949 | C74: CUST0054 | D74: Rohit | E74: Mumbai | F74: Maharashtra | G74: Perfume | H74: Beauty | I74: Fragrance | J74: 723 | K74: 1081.6977 | L74: 5 | M74: 5 | N74: =K74*L74*(1-M74/100) -> 5138.0642 | O74: =J74*L74 -> 3615 | P74: =N74-O74 -> 1523.0642 | Q74: Debit Card | R74: Delivered | S74: 44959 | T74: 6 | U74: 2 | V74: No | W74: =IF(AND(NOT(R74="Cancelled"),V74="Yes"),1,0) -> 0
A75: ORD01175 | B75: 44950 | C75: CUST0164 | D75: Suresh | E75: Kolkata | F75: West Bengal | G75: Perfume | H75: Beauty | I75: Fragrance | J75: 544 | K75: 815.51647 | L75: 3 | M75: 15 | N75: =K75*L75*(1-M75/100) -> 2079.567 | O75: =J75*L75 -> 1632 | P75: =N75-O75 -> 447.56699 | Q75: COD | R75: Delivered | S75: 44958 | T75: 4 | U75: 2 | V75: No | W75: =IF(AND(NOT(R75="Cancelled"),V75="Yes"),1,0) -> 0
A76: ORD00012 | B76: 44951 | C76: CUST0015 | D76: Arjun | E76: Ahmedabad | F76: Gujarat | G76: Headphones | H76: Electronics | I76: Accessories | J76: 979 | K76: 1111.5804 | L76: 5 | M76: 0 | N76: =K76*L76*(1-M76/100) -> 5557.902 | O76: =J76*L76 -> 4895 | P76: =N76-O76 -> 662.90197 | Q76: UPI | R76: Cancelled | T76: 8 | U76: 3 | W76: =IF(AND(NOT(R76="Cancelled"),V76="Yes"),1,0) -> 0
A77: ORD00265 | B77: 44951 | C77: CUST0287 | D77: Neha | E77: Mumbai | F77: Maharashtra | G77: iPhone 14 | H77: Electronics | I77: Mobile | J77: 71901 | K77: 73990.049 | L77: 3 | M77: 0 | N77: =K77*L77*(1-M77/100) -> 221970.15 | O77: =J77*L77 -> 215703 | P77: =N77-O77 -> 6267.1465 | Q77: Debit Card | R77: Delivered | S77: 44956 | T77: 1 | U77: 5 | V77: No | W77: =IF(AND(NOT(R77="Cancelled"),V77="Yes"),1,0) -> 0
A78: ORD00435 | B78: 44951 | C78: CUST0124 | D78: Vikram | E78: Bangalore | F78: Karnataka | G78: Sofa | H78: Home | I78: Furniture | J78: 23281 | K78: 30173.56 | L78: 1 | M78: 10 | N78: =K78*L78*(1-M78/100) -> 27156.204 | O78: =J78*L78 -> 23281 | P78: =N78-O78 -> 3875.2044 | Q78: COD | R78: Cancelled | T78: 9 | U78: 1 | W78: =IF(AND(NOT(R78="Cancelled"),V78="Yes"),1,0) -> 0
A79: ORD00678 | B79: 44951 | C79: CUST0183 | D79: Kavya | E79: Mumbai | F79: Maharashtra | G79: Headphones | H79: Electronics | I79: Accessories | J79: 1803 | K79: 3042.4848 | L79: 2 | M79: 5 | N79: =K79*L79*(1-M79/100) -> 5780.7211 | O79: =J79*L79 -> 3606 | P79: =N79-O79 -> 2174.7211 | Q79: Debit Card | R79: Cancelled | T79: 10 | U79: 1 | W79: =IF(AND(NOT(R79="Cancelled"),V79="Yes"),1,0) -> 0
A80: ORD00869 | B80: 44951 | C80: CUST0045 | D80: Nikhil | E80: Chennai | F80: Tamil Nadu | G80: Jeans | H80: Clothing | I80: Men | J80: 1492 | K80: 1734.8307 | L80: 3 | M80: 10 | N80: =K80*L80*(1-M80/100) -> 4684.0428 | O80: =J80*L80 -> 4476 | P80: =N80-O80 -> 208.04283 | Q80: Credit Card | R80: Delivered | S80: 44963 | T80: 8 | U80: 4 | V80: Yes | W80: =IF(AND(NOT(R80="Cancelled"),V80="Yes"),1,0) -> 1
A81: ORD01073 | B81: 44951 | C81: CUST0131 | D81: Rahul | E81: Hyderabad | F81: Telangana | G81: Face Cream | H81: Beauty | I81: Skincare | J81: 514 | K81: 863.92383 | L81: 1 | M81: 10 | N81: =K81*L81*(1-M81/100) -> 777.53144 | O81: =J81*L81 -> 514 | P81: =N81-O81 -> 263.53144 | Q81: COD | R81: Delivered | S81: 44960 | T81: 4 | U81: 2 | V81: No | W81: =IF(AND(NOT(R81="Cancelled"),V81="Yes"),1,0) -> 0
A82: ORD00097 | B82: 44952 | C82: CUST0216 | D82: Swathi | E82: Pune | F82: Maharashtra | G82: Perfume | H82: Beauty | I82: Fragrance | J82: 678 | K82: 910.62039 | L82: 5 | M82: 5 | N82: =K82*L82*(1-M82/100) -> 4325.4469 | O82: =J82*L82 -> 3390 | P82: =N82-O82 -> 935.44687 | Q82: Credit Card | R82: Cancelled | T82: 7 | U82: 4 | W82: =IF(AND(NOT(R82="Cancelled"),V82="Yes"),1,0) -> 0
A83: ORD00889 | B83: 44952 | C83: CUST0132 | D83: Neha | E83: Bangalore | F83: Karnataka | G83: Laptop | H83: Electronics | I83: Computers | J83: 31117 | K83: 53014.664 | L83: 3 | M83: 10 | N83: =K83*L83*(1-M83/100) -> 143139.59 | O83: =J83*L83 -> 93351 | P83: =N83-O83 -> 49788.594 | Q83: Credit Card | R83: Cancelled | T83: 7 | U83: 4 | W83: =IF(AND(NOT(R83="Cancelled"),V83="Yes"),1,0) -> 0
A84: ORD00626 | B84: 44953 | C84: CUST0057 | D84: Nikhil | E84: Hyderabad | F84: Telangana | G84: Laptop | H84: Electronics | I84: Computers | J84: 45428 | K84: 66121.672 | L84: 1 | M84: 10 | N84: =K84*L84*(1-M84/100) -> 59509.505 | O84: =J84*L84 -> 45428 | P84: =N84-O84 -> 14081.505 | Q84: UPI | R84: Cancelled | T84: 10 | U84: 1 | W84: =IF(AND(NOT(R84="Cancelled"),V84="Yes"),1,0) -> 0
A85: ORD00736 | B85: 44953 | C85: CUST0025 | D85: Anjali | E85: Pune | F85: Maharashtra | G85: Face Cream | H85: Beauty | I85: Skincare | J85: 209 | K85: 350.79626 | L85: 2 | M85: 15 | N85: =K85*L85*(1-M85/100) -> 596.35365 | O85: =J85*L85 -> 418 | P85: =N85-O85 -> 178.35365 | Q85: COD | R85: Delivered | S85: 44964 | T85: 6 | U85: 2 | V85: No | W85: =IF(AND(NOT(R85="Cancelled"),V85="Yes"),1,0) -> 0
A86: ORD00906 | B86: 44953 | C86: CUST0054 | D86: Neha | E86: Hyderabad | F86: Telangana | G86: Samsung TV | H86: Electronics | I86: TV | J86: 25798 | K86: 28104.201 | L86: 1 | M86: 20 | N86: =K86*L86*(1-M86/100) -> 22483.361 | O86: =J86*L86 -> 25798 | P86: =N86-O86 -> -3314.6392 | Q86: UPI | R86: Delivered | S86: 44962 | T86: 4 | U86: 2 | V86: No | W86: =IF(AND(NOT(R86="Cancelled"),V86="Yes"),1,0) -> 0
A87: ORD01101 | B87: 44953 | C87: CUST0185 | D87: Kiran | E87: Hyderabad | F87: Telangana | G87: Face Cream | H87: Beauty | I87: Skincare | J87: 299 | K87: 339.40117 | L87: 1 | M87: 5 | N87: =K87*L87*(1-M87/100) -> 322.43111 | O87: =J87*L87 -> 299 | P87: =N87-O87 -> 23.43111 | Q87: Credit Card | R87: Cancelled | T87: 10 | U87: 1 | W87: =IF(AND(NOT(R87="Cancelled"),V87="Yes"),1,0) -> 0
A88: ORD00057 | B88: 44954 | C88: CUST0243 | D88: Divya | E88: Pune | F88: Maharashtra | G88: Perfume | H88: Beauty | I88: Fragrance | J88: 857 | K88: 1104.0598 | L88: 2 | M88: 10 | N88: =K88*L88*(1-M88/100) -> 1987.3076 | O88: =J88*L88 -> 1714 | P88: =N88-O88 -> 273.30761 | Q88: Debit Card | R88: Delivered | S88: 44960 | T88: 2 | U88: 5 | V88: No | W88: =IF(AND(NOT(R88="Cancelled"),V88="Yes"),1,0) -> 0
A89: ORD01051 | B89: 44955 | C89: CUST0120 | D89: Amit | E89: Delhi | F89: Delhi | G89: Jeans | H89: Clothing | I89: Men | J89: 945 | K89: 1080.6696 | L89: 2 | M89: 10 | N89: =K89*L89*(1-M89/100) -> 1945.2052 | O89: =J89*L89 -> 1890 | P89: =N89-O89 -> 55.205213 | Q89: UPI | R89: Cancelled | T89: 10 | U89: 1 | W89: =IF(AND(NOT(R89="Cancelled"),V89="Yes"),1,0) -> 0
A90: ORD00842 | B90: 44956 | C90: CUST0031 | D90: Deepika | E90: Mumbai | F90: Maharashtra | G90: Shoes | H90: Clothing | I90: Footwear | J90: 2666 | K90: 4039.9621 | L90: 4 | M90: 0 | N90: =K90*L90*(1-M90/100) -> 16159.848 | O90: =J90*L90 -> 10664 | P90: =N90-O90 -> 5495.8484 | Q90: UPI | R90: Cancelled | T90: 9 | U90: 1 | W90: =IF(AND(NOT(R90="Cancelled"),V90="Yes"),1,0) -> 0
A91: ORD01063 | B91: 44956 | C91: CUST0024 | D91: Kiran | E91: Mumbai | F91: Maharashtra | G91: Face Cream | H91: Beauty | I91: Skincare | J91: 582 | K91: 785.33756 | L91: 4 | M91: 0 | N91: =K91*L91*(1-M91/100) -> 3141.3502 | O91: =J91*L91 -> 2328 | P91: =N91-O91 -> 813.35023 | Q91: Debit Card | R91: Cancelled | T91: 7 | U91: 4 | W91: =IF(AND(NOT(R91="Cancelled"),V91="Yes"),1,0) -> 0
A92: ORD00255 | B92: 44957 | C92: CUST0010 | D92: Nikhil | E92: Bangalore | F92: Karnataka | G92: Laptop | H92: Electronics | I92: Computers | J92: 40808 | K92: 70155.431 | L92: 4 | M92: 0 | N92: =K92*L92*(1-M92/100) -> 280621.73 | O92: =J92*L92 -> 163232 | P92: =N92-O92 -> 117389.73 | Q92: UPI | R92: Cancelled | T92: 9 | U92: 1 | W92: =IF(AND(NOT(R92="Cancelled"),V92="Yes"),1,0) -> 0
A93: ORD00027 | B93: 44958 | C93: CUST0286 | D93: Neha | E93: Hyderabad | F93: Telangana | G93: Mixer | H93: Home | I93: Kitchen | J93: 3464 | K93: 5180.0659 | L93: 4 | M93: 10 | N93: =K93*L93*(1-M93/100) -> 18648.237 | O93: =J93*L93 -> 13856 | P93: =N93-O93 -> 4792.2373 | Q93: COD | R93: Delivered | S93: 44966 | T93: 1 | U93: 5 | V93: No | W93: =IF(AND(NOT(R93="Cancelled"),V93="Yes"),1,0) -> 0
A94: ORD00442 | B94: 44958 | C94: CUST0009 | D94: Deepika | E94: Bangalore | F94: Karnataka | G94: Sofa | H94: Home | I94: Furniture | J94: 26453 | K94: 46272.756 | L94: 1 | M94: 5 | N94: =K94*L94*(1-M94/100) -> 43959.118 | O94: =J94*L94 -> 26453 | P94: =N94-O94 -> 17506.118 | Q94: Debit Card | R94: Delivered | S94: 44965 | T94: 1 | U94: 5 | V94: No | W94: =IF(AND(NOT(R94="Cancelled"),V94="Yes"),1,0) -> 0
A95: ORD00619 | B95: 44958 | C95: CUST0209 | D95: Pooja | E95: Delhi | F95: Delhi | G95: Dress | H95: Clothing | I95: Women | J95: 1648 | K95: 2593.6725 | L95: 1 | M95: 10 | N95: =K95*L95*(1-M95/100) -> 2334.3052 | O95: =J95*L95 -> 1648 | P95: =N95-O95 -> 686.30523 | Q95: UPI | R95: Delivered | S95: 44971 | T95: 6 | U95: 4 | V95: Yes | W95: =IF(AND(NOT(R95="Cancelled"),V95="Yes"),1,0) -> 1
A96: ORD00785 | B96: 44958 | C96: CUST0082 | D96: Amit | E96: Delhi | F96: Delhi | G96: Dress | H96: Clothing | I96: Women | J96: 1853 | K96: 1864.2706 | L96: 4 | M96: 10 | N96: =K96*L96*(1-M96/100) -> 6711.3742 | O96: =J96*L96 -> 7412 | P96: =N96-O96 -> -700.62576 | Q96: Credit Card | R96: Cancelled | T96: 8 | U96: 4 | W96: =IF(AND(NOT(R96="Cancelled"),V96="Yes"),1,0) -> 0
A97: ORD00909 | B97: 44958 | C97: CUST0246 | D97: Divya | E97: Pune | F97: Maharashtra | G97: Laptop | H97: Electronics | I97: Computers | J97: 44124 | K97: 44892.851 | L97: 2 | M97: 20 | N97: =K97*L97*(1-M97/100) -> 71828.562 | O97: =J97*L97 -> 88248 | P97: =N97-O97 -> -16419.438 | Q97: COD | R97: Delivered | S97: 44971 | T97: 6 | U97: 2 | V97: No | W97: =IF(AND(NOT(R97="Cancelled"),V97="Yes"),1,0) -> 0
A98: ORD00992 | B98: 44958 | C98: CUST0009 | D98: Neha | E98: Hyderabad | F98: Telangana | G98: Dress | H98: Clothing | I98: Women | J98: 698 | K98: 1250.8019 | L98: 1 | M98: 15 | N98: =K98*L98*(1-M98/100) -> 1063.1816 | O98: =J98*L98 -> 698 | P98: =N98-O98 -> 365.18163 | Q98: Credit Card | R98: Cancelled | T98: 9 | U98: 1 | W98: =IF(AND(NOT(R98="Cancelled"),V98="Yes"),1,0) -> 0
A99: ORD01001 | B99: 44958 | C99: CUST0202 | D99: Manoj | E99: Kolkata | F99: West Bengal | G99: Jeans | H99: Clothing | I99: Men | J99: 1161 | K99: 1946.6555 | L99: 2 | M99: 20 | N99: =K99*L99*(1-M99/100) -> 3114.6488 | O99: =J99*L99 -> 2322 | P99: =N99-O99 -> 792.64876 | Q99: Debit Card | R99: Delivered | S99: 44969 | T99: 6 | U99: 4 | V99: Yes | W99: =IF(AND(NOT(R99="Cancelled"),V99="Yes"),1,0) -> 1
A100: ORD00096 | B100: 44959 | C100: CUST0085 | D100: Suresh | E100: Mumbai | F100: Maharashtra | G100: Samsung TV | H100: Electronics | I100: TV | J100: 48512 | K100: 78496.948 | L100: 2 | M100: 15 | N100: =K100*L100*(1-M100/100) -> 133444.81 | O100: =J100*L100 -> 97024 | P100: =N100-O100 -> 36420.811 | Q100: Credit Card | R100: Cancelled | T100: 10 | U100: 1 | W100: =IF(AND(NOT(R100="Cancelled"),V100="Yes"),1,0) -> 0
...

Sheet Pivot_tables and Calculations
A1: Total Revenue | B1: =SUM(#REF!) -> #REF!
A2: Total Orders | B2: =COUNTIF(Ecommerce_Data!R2:R1711,"<>Cancelled") -> 1272
A3: Average Rating | B3: =AVERAGE(Ecommerce_Data!U:U) -> 2.903172
A4: Total Profit | B4: =SUMIF(Ecommerce_Data!R:R,"<>Cancelled",Ecommerce_Data!P:P) -> 10340627
A5: Return Rate | B5: =COUNTIF(Ecommerce_Data!V2:V1711,"Yes")/B2 -> 0.054245283
A6: Profit loss due to return | B6: =SUMIF(Ecommerce_Data!V:V,"Yes",Ecommerce_Data!P:P) -> 935462.63
A7: Profit after return | B7: =B4-B6 -> 9405164.8
E8: Returned | F8: No
E9: Order_status | F9: Delivered
E12: Category | F12: SUM of Revenue | G12: SUM of Profit | H12: AVERAGE of Rating
E13: Electronics | F13: 33344911 | G13: 6937348.1 | H13: 3.3534884
E14: Home | F14: 10183464 | G14: 2171419.8 | H14: 3.2735043
E15: Clothing | F15: 1120039.5 | G15: 235003.49 | H15: 3.5443548
E16: Beauty | F16: 285167.36 | G16: 61393.36 | H16: 3.4594595

Sheet Sheet5
B1: Top 5 Products
A2: Index | B2: Returned | C2: No
A3: 1 | B3: Order_status | C3: Delivered
A4: 2
A5: 3 | B5: Product | C5: SUM of Quantity
A6: 4 | B6: Perfume | C6: 213
A7: 5 | B7: T-Shirt | C7: 202
A8: 6 | B8: Dress | C8: 201
A9: 7 | B9: Shoes | C9: 191
A10: 8 | B10: Sofa | C10: 189
A11: 9 | B11: Laptop | C11: 179
A12: 10 | B12: Samsung TV | C12: 169
A13: 11 | B13: Jeans | C13: 156
A14: 12 | B14: Headphones | C14: 154
B15: Mixer | C15: 151
B16: iPhone 14 | C16: 147
B17: Face Cream | C17: 131

Sheet Monthly
A1: Monthly Orders Trend
A2: Order_status | B2: Delivered
A4: Order count
A5: 760
